[{"name":"정지_왼쪽앞","frames":[{"delay":150,"planes":[{"pngId":0,"x":-103,"y":-81,"transparency":100,"reverseFlag":0,"param5":0,"param6":16},{"pngId":2,"x":-57,"y":-69,"transparency":100,"reverseFlag":0,"param5":0,"param6":16},{"pngId":1,"x":-81,"y":-73,"transparency":100,"reverseFlag":0,"param5":0,"param6":16}],"effects":[]},{"delay":150,"planes":[{"pngId":0,"x":-103,"y":-81,"transparency":100,"reverseFlag":0,"param5":0,"param6":16},{"pngId":3,"x":-57,"y":-69,"transparency":100,"reverseFlag":0,"param5":0,"param6":16},{"pngId":1,"x":-81,"y":-73,"transparency":100,"reverseFlag":0,"param5":0,"param6":16}],"effects":[]},{"delay":150,"planes":[{"pngId":0,"x":-103,"y":-81,"transparency":100,"reverseFlag":0,"param5":0,"param6":16},{"pngId":4,"x":-56,"y":-71,"transparency":100,"reverseFlag":0,"param5":0,"param6":16},{"pngId":1,"x":-81,"y":-73,"transparency":100,"reverseFlag":0,"param5":0,"param6":16}],"effects":[]},{"delay":150,"planes":[{"pngId":0,"x":-103,"y":-81,"transparency":100,"reverseFlag":0,"param5":0,"param6":16},{"pngId":5,"x":-57,"y":-70,"transparency":100,"reverseFlag":0,"param5":0,"param6":16},{"pngId":1,"x":-81,"y":-73,"transparency":100,"reverseFlag":0,"param5":0,"param6":16}],"effects":[]}],"offset":0},{"name":"정지_오른쪽앞","frames":[{"delay":150,"planes":[{"pngId":0,"x":-103,"y":-81,"transparency":100,"reverseFlag":0,"param5":0,"param6":16},{"pngId":2,"x":-57,"y":-69,"transparency":100,"reverseFlag":0,"param5":0,"param6":16},{"pngId":1,"x":-81,"y":-73,"transparency":100,"reverseFlag":0,"param5":0,"param6":16}],"effects":[]},{"delay":150,"planes":[{"pngId":0,"x":-103,"y":-81,"transparency":100,"reverseFlag":0,"param5":0,"param6":16},{"pngId":3,"x":-57,"y":-69,"transparency":100,"reverseFlag":0,"param5":0,"param6":16},{"pngId":1,"x":-81,"y":-73,"transparency":100,"reverseFlag":0,"param5":0,"param6":16}],"effects":[]},{"delay":150,"planes":[{"pngId":0,"x":-103,"y":-81,"transparency":100,"reverseFlag":0,"param5":0,"param6":16},{"pngId":4,"x":-56,"y":-71,"transparency":100,"reverseFlag":0,"param5":0,"param6":16},{"pngId":1,"x":-81,"y":-73,"transparency":100,"reverseFlag":0,"param5":0,"param6":16}],"effects":[]},{"delay":150,"planes":[{"pngId":0,"x":-103,"y":-81,"transparency":100,"reverseFlag":0,"param5":0,"param6":16},{"pngId":5,"x":-57,"y":-70,"transparency":100,"reverseFlag":0,"param5":0,"param6":16},{"pngId":1,"x":-81,"y":-73,"transparency":100,"reverseFlag":0,"param5":0,"param6":16}],"effects":[]}],"offset":0},{"name":"자유행동1_왼쪽앞","frames":[{"delay":150,"planes":[{"pngId":0,"x":-103,"y":-81,"transparency":100,"reverseFlag":0,"param5":0,"param6":16},{"pngId":2,"x":-57,"y":-69,"transparency":100,"reverseFlag":0,"param5":0,"param6":16},{"pngId":1,"x":-81,"y":-73,"transparency":100,"reverseFlag":0,"param5":0,"param6":16}],"effects":[]},{"delay":150,"planes":[{"pngId":0,"x":-103,"y":-81,"transparency":100,"reverseFlag":0,"param5":0,"param6":16},{"pngId":3,"x":-57,"y":-69,"transparency":100,"reverseFlag":0,"param5":0,"param6":16},{"pngId":1,"x":-81,"y":-73,"transparency":100,"reverseFlag":0,"param5":0,"param6":16}],"effects":[]},{"delay":150,"planes":[{"pngId":0,"x":-103,"y":-81,"transparency":100,"reverseFlag":0,"param5":0,"param6":16},{"pngId":4,"x":-56,"y":-71,"transparency":100,"reverseFlag":0,"param5":0,"param6":16},{"pngId":1,"x":-81,"y":-73,"transparency":100,"reverseFlag":0,"param5":0,"param6":16}],"effects":[]},{"delay":150,"planes":[{"pngId":0,"x":-103,"y":-81,"transparency":100,"reverseFlag":0,"param5":0,"param6":16},{"pngId":5,"x":-57,"y":-70,"transparency":100,"reverseFlag":0,"param5":0,"param6":16},{"pngId":1,"x":-81,"y":-73,"transparency":100,"reverseFlag":0,"param5":0,"param6":16}],"effects":[]}],"offset":0},{"name":"자유행동1_오른쪽앞","frames":[{"delay":150,"planes":[{"pngId":0,"x":-103,"y":-81,"transparency":100,"reverseFlag":0,"param5":0,"param6":16},{"pngId":2,"x":-57,"y":-69,"transparency":100,"reverseFlag":0,"param5":0,"param6":16},{"pngId":1,"x":-81,"y":-73,"transparency":100,"reverseFlag":0,"param5":0,"param6":16}],"effects":[]},{"delay":150,"planes":[{"pngId":0,"x":-103,"y":-81,"transparency":100,"reverseFlag":0,"param5":0,"param6":16},{"pngId":3,"x":-57,"y":-69,"transparency":100,"reverseFlag":0,"param5":0,"param6":16},{"pngId":1,"x":-81,"y":-73,"transparency":100,"reverseFlag":0,"param5":0,"param6":16}],"effects":[]},{"delay":150,"planes":[{"pngId":0,"x":-103,"y":-81,"transparency":100,"reverseFlag":0,"param5":0,"param6":16},{"pngId":4,"x":-56,"y":-71,"transparency":100,"reverseFlag":0,"param5":0,"param6":16},{"pngId":1,"x":-81,"y":-73,"transparency":100,"reverseFlag":0,"param5":0,"param6":16}],"effects":[]},{"delay":150,"planes":[{"pngId":0,"x":-103,"y":-81,"transparency":100,"reverseFlag":0,"param5":0,"param6":16},{"pngId":5,"x":-57,"y":-70,"transparency":100,"reverseFlag":0,"param5":0,"param6":16},{"pngId":1,"x":-81,"y":-73,"transparency":100,"reverseFlag":0,"param5":0,"param6":16}],"effects":[]}],"offset":0},{"name":"자유행동2_왼쪽앞","frames":[{"delay":150,"planes":[{"pngId":0,"x":-103,"y":-81,"transparency":100,"reverseFlag":0,"param5":0,"param6":16},{"pngId":2,"x":-57,"y":-69,"transparency":100,"reverseFlag":0,"param5":0,"param6":16},{"pngId":1,"x":-81,"y":-73,"transparency":100,"reverseFlag":0,"param5":0,"param6":16}],"effects":[]},{"delay":150,"planes":[{"pngId":0,"x":-103,"y":-81,"transparency":100,"reverseFlag":0,"param5":0,"param6":16},{"pngId":3,"x":-57,"y":-69,"transparency":100,"reverseFlag":0,"param5":0,"param6":16},{"pngId":1,"x":-81,"y":-73,"transparency":100,"reverseFlag":0,"param5":0,"param6":16}],"effects":[]},{"delay":150,"planes":[{"pngId":0,"x":-103,"y":-81,"transparency":100,"reverseFlag":0,"param5":0,"param6":16},{"pngId":4,"x":-56,"y":-71,"transparency":100,"reverseFlag":0,"param5":0,"param6":16},{"pngId":1,"x":-81,"y":-73,"transparency":100,"reverseFlag":0,"param5":0,"param6":16}],"effects":[]},{"delay":150,"planes":[{"pngId":0,"x":-103,"y":-81,"transparency":100,"reverseFlag":0,"param5":0,"param6":16},{"pngId":5,"x":-57,"y":-70,"transparency":100,"reverseFlag":0,"param5":0,"param6":16},{"pngId":1,"x":-81,"y":-73,"transparency":100,"reverseFlag":0,"param5":0,"param6":16}],"effects":[]}],"offset":0},{"name":"자유행동2_오른쪽앞","frames":[{"delay":150,"planes":[{"pngId":0,"x":-103,"y":-81,"transparency":100,"reverseFlag":0,"param5":0,"param6":16},{"pngId":2,"x":-57,"y":-69,"transparency":100,"reverseFlag":0,"param5":0,"param6":16},{"pngId":1,"x":-81,"y":-73,"transparency":100,"reverseFlag":0,"param5":0,"param6":16}],"effects":[]},{"delay":150,"planes":[{"pngId":0,"x":-103,"y":-81,"transparency":100,"reverseFlag":0,"param5":0,"param6":16},{"pngId":3,"x":-57,"y":-69,"transparency":100,"reverseFlag":0,"param5":0,"param6":16},{"pngId":1,"x":-81,"y":-73,"transparency":100,"reverseFlag":0,"param5":0,"param6":16}],"effects":[]},{"delay":150,"planes":[{"pngId":0,"x":-103,"y":-81,"transparency":100,"reverseFlag":0,"param5":0,"param6":16},{"pngId":4,"x":-56,"y":-71,"transparency":100,"reverseFlag":0,"param5":0,"param6":16},{"pngId":1,"x":-81,"y":-73,"transparency":100,"reverseFlag":0,"param5":0,"param6":16}],"effects":[]},{"delay":150,"planes":[{"pngId":0,"x":-103,"y":-81,"transparency":100,"reverseFlag":0,"param5":0,"param6":16},{"pngId":5,"x":-57,"y":-70,"transparency":100,"reverseFlag":0,"param5":0,"param6":16},{"pngId":1,"x":-81,"y":-73,"transparency":100,"reverseFlag":0,"param5":0,"param6":16}],"effects":[]}],"offset":0}]