[{"name":"63897","frames":[{"delay":50,"planes":[{"pngId":0,"x":-12,"y":-13,"transparency":100,"reverseFlag":0,"param5":0,"param6":16}],"effects":[]}],"offset":0},{"name":"63903","frames":[{"delay":50,"planes":[{"pngId":1,"x":-12,"y":-13,"transparency":100,"reverseFlag":0,"param5":0,"param6":16}],"effects":[]}],"offset":0},{"name":"63909","frames":[{"delay":50,"planes":[{"pngId":9,"x":-15,"y":-16,"transparency":100,"reverseFlag":0,"param5":0,"param6":16}],"effects":[]}],"offset":0},{"name":"63910","frames":[{"delay":50,"planes":[{"pngId":8,"x":-15,"y":-16,"transparency":100,"reverseFlag":0,"param5":0,"param6":16}],"effects":[]}],"offset":0},{"name":"63911","frames":[{"delay":50,"planes":[{"pngId":6,"x":-15,"y":-13,"transparency":100,"reverseFlag":0,"param5":0,"param6":16}],"effects":[]}],"offset":0},{"name":"63912","frames":[{"delay":50,"planes":[{"pngId":7,"x":-14,"y":-12,"transparency":100,"reverseFlag":0,"param5":0,"param6":16}],"effects":[]}],"offset":0},{"name":"63913","frames":[{"delay":50,"planes":[{"pngId":2,"x":-10,"y":-19,"transparency":100,"reverseFlag":0,"param5":0,"param6":16}],"effects":[]}],"offset":0},{"name":"63914","frames":[{"delay":50,"planes":[{"pngId":3,"x":-15,"y":-13,"transparency":100,"reverseFlag":0,"param5":0,"param6":16}],"effects":[]}],"offset":0},{"name":"63915","frames":[{"delay":50,"planes":[{"pngId":4,"x":-12,"y":-9,"transparency":100,"reverseFlag":0,"param5":0,"param6":16}],"effects":[]}],"offset":0},{"name":"63916","frames":[{"delay":50,"planes":[{"pngId":5,"x":-11,"y":-15,"transparency":100,"reverseFlag":0,"param5":0,"param6":16}],"effects":[]}],"offset":0}]